setup.py
lsc_tictactoe/TicTacToe.py
lsc_tictactoe/__init__.py
lsc_tictactoe.egg-info/PKG-INFO
lsc_tictactoe.egg-info/SOURCES.txt
lsc_tictactoe.egg-info/dependency_links.txt
lsc_tictactoe.egg-info/not-zip-safe
lsc_tictactoe.egg-info/top_level.txt