Metadata-Version: 1.0
Name: lsc-tictactoe
Version: 0.3
Summary: Tic Tac Toe Game
Home-page: UNKNOWN
Author: Lucian Stefan Craciun
Author-email: lucyans_c@yahoo.com
License: UNKNOWN
Platform: UNKNOWN
